david4you-0.1.2.data/scripts/david
davidlol/__init__.py
david4you-0.1.2.dist-info/LICENSE.txt
david4you-0.1.2.dist-info/METADATA
david4you-0.1.2.dist-info/WHEEL
david4you-0.1.2.dist-info/top_level.txt
david4you-0.1.2.dist-info/RECORD
