Metadata-Version: 2.1
Name: david4you
Version: 0.1.2
Summary: A very basic tool
Home-page: https://github.com/all-drama/psychic
Author: DaviD
Author-email: david@s.org
License: MIT
Keywords: davidlol
Classifier: Development Status :: 5 - Production/Stable
Classifier: Intended Audience :: Education
Classifier: Operating System :: Microsoft :: Windows :: Windows 10
Classifier: License :: OSI Approved :: MIT License
Classifier: Programming Language :: Python :: 3
License-File: LICENSE.txt
Requires-Dist: requests
